fastsio/__init__.py
fastsio/admin.py
fastsio/asgi.py
fastsio/async_admin.py
fastsio/async_aiopika_manager.py
fastsio/async_client.py
fastsio/async_manager.py
fastsio/async_namespace.py
fastsio/async_pubsub_manager.py
fastsio/async_redis_manager.py
fastsio/async_server.py
fastsio/async_simple_client.py
fastsio/asyncapi.py
fastsio/base_client.py
fastsio/base_manager.py
fastsio/base_namespace.py
fastsio/base_server.py
fastsio/client.py
fastsio/dependency.py
fastsio/exceptions.py
fastsio/kafka_manager.py
fastsio/kombu_manager.py
fastsio/manager.py
fastsio/middleware.py
fastsio/middlewares.py
fastsio/msgpack_packet.py
fastsio/namespace.py
fastsio/packet.py
fastsio/pubsub_manager.py
fastsio/redis_manager.py
fastsio/router.py
fastsio/server.py
fastsio/simple_client.py
fastsio/tornado.py
fastsio/types.py
fastsio/zmq_manager.py
fastsio-0.3.4.dist-info/LICENSE
fastsio-0.3.4.dist-info/METADATA
fastsio-0.3.4.dist-info/WHEEL
fastsio-0.3.4.dist-info/RECORD
