Metadata-Version: 2.1
Name: fastsio
Version: 0.3.4
Summary: light and typization Socket.IO server and client for Python
Home-page: https://github.com/cicwak/fastsio
License: MIT
Author: Miguel Grinberg
Author-email: miguel.grinberg@gmail.com
Requires-Python: >=3.9
Classifier: License :: OSI Approved :: MIT License
Classifier: Programming Language :: Python :: 3
Classifier: Programming Language :: Python :: 3.9
Classifier: Programming Language :: Python :: 3.10
Classifier: Programming Language :: Python :: 3.11
Classifier: Programming Language :: Python :: 3.12
Provides-Extra: asyncio-client
Provides-Extra: client
Provides-Extra: docs
Requires-Dist: aiohttp (>=3.4) ; extra == "asyncio-client"
Requires-Dist: bidict (>=0.21.0)
Requires-Dist: msgpack (>=1.1.1,<2.0.0)
Requires-Dist: pydantic (>=2.11.7,<3.0.0)
Requires-Dist: python-engineio (>=4.12.2,<5.0.0)
Requires-Dist: requests (>=2.21.0) ; extra == "client"
Requires-Dist: sphinx ; extra == "docs"
Requires-Dist: websocket-client (>=0.54.0) ; extra == "client"
Project-URL: Repository, https://github.com/cicwak/fastsio
